Metadata-Version: 2.1
Name: plasmidCC
Version: 1.0.0
Summary: A Centrifuge based plasmid prediction tool
License-File: LICENSE
Requires-Dist: biopython>=1.83
Requires-Dist: numpy>=1.26.4
Requires-Dist: pandas>=2.2.0
Requires-Dist: rich>=13.7.0
Requires-Dist: urllib3>=2.2.0
